LICENSE
MANIFEST.in
README.rst
patchit.py
setup.py
tests.py
assets/a.patch
assets/b.patch
assets/c.patch
assets/d.patch
assets/original_a.txt
assets/original_d.txt
assets/patch_a.diff
patchit.egg-info/PKG-INFO
patchit.egg-info/SOURCES.txt
patchit.egg-info/dependency_links.txt
patchit.egg-info/top_level.txt